pyros_config/__init__.py
pyros_config/__main__.py
pyros_config/_version.py
pyros_config/config.py
pyros_config/confighandler.py
pyros_config/helpers.py
pyros_config/packagebound.py
pyros_config/tests/__init__.py
pyros_config/tests/test_helpers.py
pyros_config-0.2.0.dist-info/DESCRIPTION.rst
pyros_config-0.2.0.dist-info/METADATA
pyros_config-0.2.0.dist-info/RECORD
pyros_config-0.2.0.dist-info/WHEEL
pyros_config-0.2.0.dist-info/entry_points.txt
pyros_config-0.2.0.dist-info/metadata.json
pyros_config-0.2.0.dist-info/top_level.txt
