Metadata-Version: 2.0
Name: pyros-config
Version: 0.2.0
Summary: Classes to manage a server configuration. Heavily inspired by flask
Home-page: http://github.com/asmodehn/pyros-config
Author: AlexV
Author-email: asmodehn@gmail.com
License: BSD
Platform: UNKNOWN
Requires-Dist: six
Requires-Dist: pytest
